airbyte_agent_zendesk_chat/__init__.py
airbyte_agent_zendesk_chat/connector.py
airbyte_agent_zendesk_chat/connector_model.py
airbyte_agent_zendesk_chat/models.py
airbyte_agent_zendesk_chat/types.py
airbyte_agent_zendesk_chat/_vendored/__init__.py
airbyte_agent_zendesk_chat/_vendored/connector_sdk/__init__.py
airbyte_agent_zendesk_chat/_vendored/connector_sdk/auth_strategies.py
airbyte_agent_zendesk_chat/_vendored/connector_sdk/auth_template.py
airbyte_agent_zendesk_chat/_vendored/connector_sdk/connector_model_loader.py
airbyte_agent_zendesk_chat/_vendored/connector_sdk/constants.py
airbyte_agent_zendesk_chat/_vendored/connector_sdk/exceptions.py
airbyte_agent_zendesk_chat/_vendored/connector_sdk/extensions.py
airbyte_agent_zendesk_chat/_vendored/connector_sdk/http_client.py
airbyte_agent_zendesk_chat/_vendored/connector_sdk/introspection.py
airbyte_agent_zendesk_chat/_vendored/connector_sdk/secrets.py
airbyte_agent_zendesk_chat/_vendored/connector_sdk/types.py
airbyte_agent_zendesk_chat/_vendored/connector_sdk/utils.py
airbyte_agent_zendesk_chat/_vendored/connector_sdk/validation.py
airbyte_agent_zendesk_chat/_vendored/connector_sdk/validation_replication.py
airbyte_agent_zendesk_chat/_vendored/connector_sdk/cloud_utils/__init__.py
airbyte_agent_zendesk_chat/_vendored/connector_sdk/cloud_utils/client.py
airbyte_agent_zendesk_chat/_vendored/connector_sdk/executor/__init__.py
airbyte_agent_zendesk_chat/_vendored/connector_sdk/executor/hosted_executor.py
airbyte_agent_zendesk_chat/_vendored/connector_sdk/executor/local_executor.py
airbyte_agent_zendesk_chat/_vendored/connector_sdk/executor/models.py
airbyte_agent_zendesk_chat/_vendored/connector_sdk/http/__init__.py
airbyte_agent_zendesk_chat/_vendored/connector_sdk/http/config.py
airbyte_agent_zendesk_chat/_vendored/connector_sdk/http/exceptions.py
airbyte_agent_zendesk_chat/_vendored/connector_sdk/http/protocols.py
airbyte_agent_zendesk_chat/_vendored/connector_sdk/http/response.py
airbyte_agent_zendesk_chat-0.1.26.dist-info/METADATA
airbyte_agent_zendesk_chat-0.1.26.dist-info/WHEEL
airbyte_agent_zendesk_chat-0.1.26.dist-info/RECORD
